g4f/__init__.py
g4f/__main__.py
g4f/config.py
g4f/cookies.py
g4f/debug.py
g4f/errors.py
g4f/files.py
g4f/models.py
g4f/typing.py
g4f/version.py
g4f/Provider/ApiAirforce.py
g4f/Provider/Chatai.py
g4f/Provider/Cloudflare.py
g4f/Provider/Copilot.py
g4f/Provider/DeepInfra.py
g4f/Provider/EasyChat.py
g4f/Provider/GLM.py
g4f/Provider/GradientNetwork.py
g4f/Provider/ItalyGPT.py
g4f/Provider/LambdaChat.py
g4f/Provider/Mintlify.py
g4f/Provider/OIVSCodeSer.py
g4f/Provider/OperaAria.py
g4f/Provider/Perplexity.py
g4f/Provider/PollinationsAI.py
g4f/Provider/PollinationsImage.py
g4f/Provider/Qwen.py
g4f/Provider/Startnest.py
g4f/Provider/StringableInference.py
g4f/Provider/TeachAnything.py
g4f/Provider/WeWordle.py
g4f/Provider/Yqcloud.py
g4f/Provider/Yupp.py
g4f/Provider/__init__.py
g4f/Provider/base_provider.py
g4f/Provider/helper.py
g4f/Provider/audio/EdgeTTS.py
g4f/Provider/audio/MarkItDown.py
g4f/Provider/audio/OpenAIFM.py
g4f/Provider/audio/__init__.py
g4f/Provider/audio/gTTS.py
g4f/Provider/hf_space/BAAI_Ling.py
g4f/Provider/hf_space/BlackForestLabs_Flux1Dev.py
g4f/Provider/hf_space/BlackForestLabs_Flux1KontextDev.py
g4f/Provider/hf_space/CohereForAI_C4AI_Command.py
g4f/Provider/hf_space/DeepseekAI_JanusPro7b.py
g4f/Provider/hf_space/Microsoft_Phi_4_Multimodal.py
g4f/Provider/hf_space/Qwen_Qwen_2_5.py
g4f/Provider/hf_space/Qwen_Qwen_2_5M.py
g4f/Provider/hf_space/Qwen_Qwen_2_5_Max.py
g4f/Provider/hf_space/Qwen_Qwen_2_72B.py
g4f/Provider/hf_space/Qwen_Qwen_3.py
g4f/Provider/hf_space/StabilityAI_SD35Large.py
g4f/Provider/hf_space/__init__.py
g4f/Provider/hf_space/raise_for_status.py
g4f/Provider/local/Local.py
g4f/Provider/local/Ollama.py
g4f/Provider/local/__init__.py
g4f/Provider/needs_auth/AIBadgr.py
g4f/Provider/needs_auth/Anthropic.py
g4f/Provider/needs_auth/Azure.py
g4f/Provider/needs_auth/BingCreateImages.py
g4f/Provider/needs_auth/BlackboxPro.py
g4f/Provider/needs_auth/CablyAI.py
g4f/Provider/needs_auth/Cerebras.py
g4f/Provider/needs_auth/Claude.py
g4f-6.8.2.dist-info/licenses/LICENSE
g4f-6.8.2.dist-info/METADATA
g4f-6.8.2.dist-info/WHEEL
g4f-6.8.2.dist-info/entry_points.txt
g4f-6.8.2.dist-info/top_level.txt
g4f-6.8.2.dist-info/RECORD
