Metadata-Version: 2.4
Name: g4f
Version: 6.8.2
Summary: The official gpt4free repository | various collection of powerful language models
Home-page: https://github.com/xtekky/gpt4free
Author: Tekky
Author-email: <support@g4f.ai>
Project-URL: Source Code, https://github.com/xtekky/gpt4free
Project-URL: Bug Tracker, https://github.com/xtekky/gpt4free/issues
Keywords: gpt4free,gpt4free.js,g4f,g4f.dev,javascript,npm,browser,gpt,chatgpt,deepseek,openai,ai,client,sdk,free,ai,gpt-4,gpt-4o,chat,api,browser,ai,ai,js,client,text,generation,image,generation,in-browser,ai,frontend,ai,openai,alternative,javascript,ai,library,nodejs,prompt,engineering,chatbot,ai,integration
Classifier: Development Status :: 2 - Pre-Alpha
Classifier: Intended Audience :: Developers
Classifier: Programming Language :: Python :: 3
Classifier: Operating System :: Unix
Classifier: Operating System :: MacOS :: MacOS X
Classifier: Operating System :: Microsoft :: Windows
License-File: LICENSE
Requires-Dist: requests
Requires-Dist: aiohttp
Requires-Dist: brotli
Requires-Dist: pycryptodome
Requires-Dist: nest_asyncio
Provides-Extra: all
Requires-Dist: curl_cffi>=0.6.2; extra == "all"
Requires-Dist: certifi; extra == "all"
Requires-Dist: browser_cookie3; extra == "all"
Requires-Dist: ddgs; extra == "all"
Requires-Dist: beautifulsoup4; extra == "all"
Requires-Dist: platformdirs; extra == "all"
Requires-Dist: aiohttp_socks; extra == "all"
Requires-Dist: pillow; extra == "all"
Requires-Dist: cairosvg; extra == "all"
Requires-Dist: werkzeug; extra == "all"
Requires-Dist: flask; extra == "all"
Requires-Dist: fastapi; extra == "all"
Requires-Dist: uvicorn; extra == "all"
Requires-Dist: nodriver; extra == "all"
Requires-Dist: python-multipart; extra == "all"
Requires-Dist: a2wsgi; extra == "all"
Requires-Dist: setuptools; extra == "all"
Requires-Dist: markitdown[all]; extra == "all"
Requires-Dist: python-dotenv; extra == "all"
Requires-Dist: aiofile; extra == "all"
Provides-Extra: slim
Requires-Dist: curl_cffi>=0.6.2; extra == "slim"
Requires-Dist: certifi; extra == "slim"
Requires-Dist: browser_cookie3; extra == "slim"
Requires-Dist: ddgs; extra == "slim"
Requires-Dist: beautifulsoup4; extra == "slim"
Requires-Dist: aiohttp_socks; extra == "slim"
Requires-Dist: pillow; extra == "slim"
Requires-Dist: werkzeug; extra == "slim"
Requires-Dist: flask; extra == "slim"
Requires-Dist: fastapi; extra == "slim"
Requires-Dist: uvicorn; extra == "slim"
Requires-Dist: nodriver; extra == "slim"
Requires-Dist: python-multipart; extra == "slim"
Requires-Dist: a2wsgi; extra == "slim"
Requires-Dist: pypdf2; extra == "slim"
Requires-Dist: python-docx; extra == "slim"
Requires-Dist: python-dotenv; extra == "slim"
Requires-Dist: aiofile; extra == "slim"
Provides-Extra: image
Requires-Dist: pillow; extra == "image"
Requires-Dist: cairosvg; extra == "image"
Requires-Dist: beautifulsoup4; extra == "image"
Provides-Extra: webview
Requires-Dist: pywebview; extra == "webview"
Requires-Dist: platformdirs; extra == "webview"
Requires-Dist: plyer; extra == "webview"
Requires-Dist: cryptography; extra == "webview"
Provides-Extra: api
Requires-Dist: loguru; extra == "api"
Requires-Dist: fastapi; extra == "api"
Requires-Dist: uvicorn; extra == "api"
Requires-Dist: python-multipart; extra == "api"
Requires-Dist: a2wsgi; extra == "api"
Provides-Extra: gui
Requires-Dist: werkzeug; extra == "gui"
Requires-Dist: flask; extra == "gui"
Requires-Dist: beautifulsoup4; extra == "gui"
Requires-Dist: pillow; extra == "gui"
Provides-Extra: search
Requires-Dist: beautifulsoup4; extra == "search"
Requires-Dist: pillow; extra == "search"
Requires-Dist: ddgs; extra == "search"
Provides-Extra: local
Requires-Dist: gpt4all; extra == "local"
Provides-Extra: files
Requires-Dist: beautifulsoup4; extra == "files"
Requires-Dist: markitdown[all]; extra == "files"
Dynamic: author
Dynamic: author-email
Dynamic: classifier
Dynamic: description
Dynamic: description-content-type
Dynamic: home-page
Dynamic: keywords
Dynamic: license-file
Dynamic: project-url
Dynamic: provides-extra
Dynamic: requires-dist
Dynamic: summary
